{"topics": [{
  "topics": [
    {
      "property": "ConceptSectionUuids",
      "title": "UAE Holidays",
      "matching": "8936C15A-E82F-4726-A6F8-99F5B30D7AB8"
    },
    {
      "property": "ConceptSectionUuids",
      "title": "Coronavirus",
      "matching": "A7F50D98-8761-4D23-909B-A6324E735691"
    },
    {
      "property": "ConceptSectionUuids",
      "title": "Expo City Dubai",
      "matching": "2ca9b084-41d2-4f40-9a83-d9c858e87eb4"
    },
    {
      "property": "ConceptSectionUuids",
      "title": "Year of the 50th",
      "matching": "1e0f118f-badd-4206-9e11-a3d66a9fe557"
    },
    {
      "property": "ConceptSectionUuids",
      "title": "Crime and Courts",
      "matching": "8915BCC2-B4CE-4CA9-AF52-CB86A103E7EA"
    },
    {
      "property": "ConceptSectionUuids",
      "title": "Education",
      "matching": "7DEAE0E3-AE2E-4E03-AFC4-944F22EAD1A7"
    },
    {
      "property": "ConceptSectionUuids",
      "title": "Emergencies",
      "matching": "ED5B871D-7BFC-433F-91E1-531FEE938A60"
    },
    {
      "property": "ConceptSectionUuids",
      "title": "Government",
      "matching": "1AA3B43B-7CC5-4BCB-83B6-5F60BD607FC2"
    },
    {
      "property": "ConceptSectionUuids",
      "title": "Healthcare",
      "matching": "B4A52445-36DF-4754-BD5B-0AB042AFF03E"
    },
    {
      "property": "ConceptSectionUuids",
      "title": "Legal",
      "matching": "B4A8445D-CC80-4862-9F05-BF4462A56582"
    },
    {
      "property": "ConceptSectionUuids",
      "title": "Transport",
      "matching": "D9846646-FDC9-45BF-9C99-47E7C7B2883D"
    },
    {
      "property": "ConceptSectionUuids",
      "title": "Community",
      "matching": "57DBDAD9-A4B1-4B19-BAD5-C3D3E489E7BA"
    },
    {
      "property": "ConceptSectionUuids",
      "title": "Weather",
      "matching": "54CE0F42-3D0C-43F5-97A3-8DC2690F3706"
    },
    {
      "property": "ConceptSectionUuids",
      "title": "My UAE",
      "matching": "e4254275-e6f5-4f87-a411-ad1663065306"
    },
    {
      "property": "ConceptSectionUuids",
      "title": "Gulf",
      "matching": "08444880-2F4B-4BD0-A1D0-A58D82CD3B3D"
    },
    {
      "property": "ConceptSectionUuids",
      "title": "Business",
      "matching": "1DB7519B-DFB8-4102-8094-F4674422C664"
    },
    {
      "property": "ConceptSectionUuids",
      "title": "Your money",
      "matching": "7804173C-4747-4607-8F82-B98EA1160D7C"
    },
    {
      "property": "ConceptSectionUuids",
      "title": "Food",
      "matching": "F099F2DD-6F83-4793-81E3-75BFC8EB23EA"
    },
    {
      "property": "ConceptSectionUuids",
      "title": "Parenting",
      "matching": "96bbfcfb-6b7c-4b5b-b82a-c73dbbe1a1bb"
    },
    {
      "property": "ConceptSectionUuids",
      "title": "World",
      "matching": "F7647EED-61BF-4444-98CB-8B28E185083E"
    },
    {
      "property": "ConceptSectionUuids",
      "title": "Opinion",
      "matching": "BB1BA6E4-8BF7-4D8E-A388-21D85EB1FE11"
    },
    {
      "property": "ConceptSectionUuids",
      "title": "Sport",
      "matching": "09D69DC2-9CFB-4DF9-B1D6-74E83EBB4BC7"
    },
    {
      "property": "ConceptSectionUuids",
      "title": "Entertainment",
      "matching": "7CF70BE9-50EC-42E9-96DC-2E809FC202B0"
    },
    {
      "property": "ConceptSectionUuids",
      "title": "Events",
      "matching": "8EDC6BBF-6763-48B0-B023-F84C38E0CD94"
    },
    {
      "property": "ConceptSectionUuids",
      "title": "Auto",
      "matching": "3E934A14-12EC-4DBE-817B-C3D35B1808D8"
    },
    {
      "property": "ConceptSectionUuids",
      "title": "Lifestyle",
      "matching": "676FDE69-53F6-4317-A41E-7AAF3864DFE8"
    },
    {
      "property": "ConceptSectionUuids",
      "title": "Jobs",
      "matching": "7339e923-393d-463a-b721-97a1aa8d5104"
    },
    {
      "property": "ConceptSectionUuids",
      "title": "Tech",
      "matching": "F3F784E9-3249-49E7-90B6-2F1661290F5F"
    },
    {
      "property": "ConceptSectionUuids",
      "title": "Travel",
      "matching": "2EEDD512-1968-4159-8F63-9BECB14C7562"
    },
    {
      "property": "ConceptSectionUuids",
      "title": "UAE",
      "matching": "A972DD74-0236-4162-BF80-31D96DE6490D"
    },
    {
      "property": "ConceptSectionUuids",
      "title": "City Times",
      "matching": "CB3617E3-7A40-41F5-9E59-C01A9B3076A9"
    },
    {
      "property": "ConceptSectionUuids",
      "title": "WKND",
      "matching": "DCA8F478-606B-4FA2-8F10-103402C72633"
    },
    {
      "property": "ConceptSectionUuids",
      "title": "Long Reads",
      "matching": "5cbeebcb-838d-4c9c-93b7-431dfdd1a79c"
    },
    {
      "property": "ConceptSectionUuids",
      "title": "Art and Culture",
      "matching": "87EB71E0-EB24-40D4-ADD0-4412E3AAC366"
    },
    {
      "property": "ConceptSectionUuids",
      "title": "Games",
      "matching": "74bc32a0-08fb-44d4-83da-9a3f09dc8b46"
    },
    {
      "property": "ConceptSectionUuids",
      "title": "KT Engage",
      "matching": "d201c92c-73de-43c6-92a9-a640733277f5"
    },
    {
      "property": "ConceptSectionUuids",
      "title": "KT Impact",
      "matching": "9defee38-bd87-465f-8719-dfeadf63aeeb"
    },
    {
      "property": "ConceptSectionUuids",
      "title": "KT Network",
      "matching": "e137a534-5445-4703-85ba-269602613922"
    }
  ],
  "title": "Topics"
}]}